esp_docs/__init__.py
esp_docs/build_docs.py
esp_docs/check_docs.py
esp_docs/conf_docs.py
esp_docs/constants.py
esp_docs/deploy_docs.py
esp_docs/get_github_rev.py
esp_docs/sanitize_version.py
esp_docs/_static/DejaVuSans.ttf
esp_docs/_static/NotoSansSC-Regular.otf
esp_docs/_static/espressif-logo.svg
esp_docs/_static/espressif2.pdf
esp_docs/_static/theme_overrides.css
esp_docs/esp_extensions/__init__.py
esp_docs/esp_extensions/add_html_zip.py
esp_docs/esp_extensions/exclude_docs.py
esp_docs/esp_extensions/format_esp_target.py
esp_docs/esp_extensions/include_build_file.py
esp_docs/esp_extensions/latex_builder.py
esp_docs/esp_extensions/link_roles.py
esp_docs/esp_extensions/run_doxygen.py
esp_docs/esp_extensions/dummy_build_system/__init__.py
esp_docs/fonts/DejaVuSans.ttf
esp_docs/fonts/NotoSansSC-Regular.otf
esp_docs/generic_extensions/__init__.py
esp_docs/generic_extensions/add_warnings.py
esp_docs/generic_extensions/google_analytics.py
esp_docs/generic_extensions/html_redirects.py
esp_docs/generic_extensions/list_filter.py
esp_docs/generic_extensions/toctree_filter.py
esp_docs/idf_extensions/__init__.py
esp_docs/idf_extensions/esp_err_definitions.py
esp_docs/idf_extensions/gen_defines.py
esp_docs/idf_extensions/gen_idf_tools_links.py
esp_docs/idf_extensions/gen_toolchain_links.py
esp_docs/idf_extensions/gen_version_specific_includes.py
esp_docs/idf_extensions/kconfig_reference.py
esp_docs/idf_extensions/build_system/CMakeLists.txt
esp_docs/idf_extensions/build_system/__init__.py
esp_docs/latex_templates/espidf.sty
esp_docs/latex_templates/preamble.tex
esp_docs/latex_templates/titlepage.tex
esp_docs/util/__init__.py
esp_docs/util/util.py
esp_docs/vendor/blockdiag/__init__.py
esp_docs/vendor/blockdiag/builder.py
esp_docs/vendor/blockdiag/command.py
esp_docs/vendor/blockdiag/drawer.py
esp_docs/vendor/blockdiag/elements.py
esp_docs/vendor/blockdiag/metrics.py
esp_docs/vendor/blockdiag/parser.py
esp_docs/vendor/blockdiag/imagedraw/__init__.py
esp_docs-2.1.3.dist-info/METADATA
esp_docs-2.1.3.dist-info/WHEEL
esp_docs-2.1.3.dist-info/entry_points.txt
esp_docs-2.1.3.dist-info/top_level.txt
esp_docs-2.1.3.dist-info/RECORD
