Metadata-Version: 2.1
Name: esp-docs
Version: 2.1.3
Summary: Documentation building package used at Espressif
Home-page: https://github.com/espressif/esp-docs
Author: Espressif
Author-email: marius.vikhammer@espressif.com
Project-URL: Bug Tracker, https://github.com/espressif/esp-docs/issues
Classifier: Programming Language :: Python :: 3
Classifier: License :: OSI Approved :: MIT License
Classifier: Operating System :: OS Independent
Requires-Python: >=3.8
Requires-Dist: docutils<0.21
Requires-Dist: cairosvg==2.5.1
Requires-Dist: sphinx~=7.1.2
Requires-Dist: breathe==4.35.0
Requires-Dist: sphinx-copybutton==0.5.0
Requires-Dist: sphinx-notfound-page
Requires-Dist: seqdiag==3.0.0
Requires-Dist: actdiag==3.0.0
Requires-Dist: sphinxcontrib-blockdiag==3.0.0
Requires-Dist: sphinxcontrib-seqdiag==3.0.0
Requires-Dist: sphinxcontrib-actdiag==3.0.0
Requires-Dist: sphinxcontrib-nwdiag==2.0.0
Requires-Dist: sphinxcontrib-wavedrom<3.1,>=3.0
Requires-Dist: sphinxcontrib-svg2pdfconverter[cairosvg]==1.2.0
Requires-Dist: nwdiag==2.0.0
Requires-Dist: recommonmark
Requires-Dist: sphinx-selective-exclude==1.0.3
Requires-Dist: sphinx-idf-theme==2.0.1
